{
  "type": "FeatureCollection",
  "source": "IBGE CNEFE + Faces de Logradouros - 2022",
  "generator": "CSV-CNEFE2GeoJSON.lua 1.5.7 - fidelis.assis@gmail.com",
  "date": "2025-02-02T09:05:23-0300",
  "features": [
    {
      "type": "Feature",
      "properties": { 
      "IBGE:COD_UNICO_ENDERECO": "112590036",
      "addr:housenumber": "24",
      "addr:postcode": "48619-899",
      "addr:street": "Estrada da BR-110 A Casa de Pedra",
      "addr:suburb": "Dois Riachos",
      "addr:unit": "E Piquete",
      "amenity": "animal_breeding",
      "animal_breeding": "cow",
      "fixme": "Confirmar nome;Verificar coordenadas",
      "landuse": "farmyard",
      "name": "Criação de Bovinos",
      "note": "Sem setor ou quadra no bayface do IBGE 0500-0241P-0-112"
      },
      "geometry": {
         "type": "Point",
         "coordinates": [-38.240823,-9.596875]
      }
    },
    {
      "type": "Feature",
      "properties": { 
      "IBGE:COD_UNICO_ENDERECO": "27413926",
      "addr:housenumber": "50 A",
      "addr:postcode": "48619-899",
      "addr:street": "Estrada da Casa de Pedra ao Riacho",
      "addr:suburb": "Dois Riachos",
      "building": "yes",
      "fixme": "Verificar coordenadas",
      "note": "Sem setor ou quadra no bayface do IBGE 0500-0241P-0-110"
      },
      "geometry": {
         "type": "Point",
         "coordinates": [-38.263282,-9.591249]
      }
    },
    {
      "type": "Feature",
      "properties": { 
      "IBGE:COD_UNICO_ENDERECO": "112590632",
      "addr:housenumber": "10 A",
      "addr:postcode": "48619-899",
      "addr:street": "Estrada da Casa de Pedra ao Riacho",
      "addr:suburb": "Dois Riachos",
      "amenity": "animal_breeding",
      "animal_breeding": "cow",
      "fixme": "Confirmar nome;Verificar coordenadas",
      "landuse": "farmyard",
      "name": "Criação de Bovinos",
      "note": "Sem setor ou quadra no bayface do IBGE 0500-0241P-0-110"
      },
      "geometry": {
         "type": "Point",
         "coordinates": [-38.248971,-9.581232]
      }
    },
    {
      "type": "Feature",
      "properties": { 
      "IBGE:COD_UNICO_ENDERECO": "27413803",
      "addr:housenumber": "17",
      "addr:postcode": "48619-899",
      "addr:street": "Estrada da Casa de Pedra ao Riacho",
      "addr:suburb": "Dois Riachos",
      "addr:unit": "E Piquete",
      "building": "yes",
      "fixme": "Verificar coordenadas",
      "note": "Sem setor ou quadra no bayface do IBGE 0500-0241P-0-110"
      },
      "geometry": {
         "type": "Point",
         "coordinates": [-38.245913,-9.591205]
      }
    }
  ]
}
