{
  "type": "FeatureCollection",
  "source": "IBGE CNEFE + Faces de Logradouros - 2022",
  "generator": "CSV-CNEFE2GeoJSON.lua 1.5.7 - fidelis.assis@gmail.com",
  "date": "2025-02-02T09:05:06-0300",
  "features": [
    {
      "type": "Feature",
      "properties": { 
      "IBGE:COD_UNICO_ENDERECO": "112589946",
      "addr:housenumber": "449020",
      "addr:postcode": "48619-899",
      "addr:street": "Acesso do Bogo ao Alto da Burra",
      "addr:suburb": "Alto da Burra",
      "addr:unit": "Cisterna",
      "building": "yes",
      "fixme": "Verificar coordenadas",
      "note": "Sem setor ou quadra no bayface do IBGE 0500-0241P-0-98"
      },
      "geometry": {
         "type": "Point",
         "coordinates": [-38.276472,-9.648073]
      }
    },
    {
      "type": "Feature",
      "properties": { 
      "IBGE:COD_UNICO_ENDERECO": "192034332",
      "addr:housenumber": "97",
      "addr:postcode": "48619-899",
      "addr:street": "Acesso do Bogo ao Alto da Burra",
      "addr:suburb": "Alto da Burra",
      "building": "yes",
      "fixme": "Verificar coordenadas",
      "note": "Sem setor ou quadra no bayface do IBGE 0500-0241P-0-98"
      },
      "geometry": {
         "type": "Point",
         "coordinates": [-38.275462,-9.648368]
      }
    },
    {
      "type": "Feature",
      "properties": { 
      "IBGE:COD_UNICO_ENDERECO": "192034330",
      "addr:housenumber": "70 A",
      "addr:postcode": "48619-899",
      "addr:street": "Acesso do Bogo ao Alto da Burra",
      "addr:suburb": "Alto da Burra",
      "building": "yes",
      "fixme": "Verificar coordenadas",
      "note": "Sem setor ou quadra no bayface do IBGE 0500-0241P-0-98"
      },
      "geometry": {
         "type": "Point",
         "coordinates": [-38.275695,-9.649217]
      }
    },
    {
      "type": "Feature",
      "properties": { 
      "IBGE:COD_UNICO_ENDERECO": "112589980",
      "addr:housenumber": "90 C",
      "addr:postcode": "48619-899",
      "addr:suburb": "Alto da Burra",
      "building": "yes",
      "fixme": "Verificar coordenadas",
      "note": "Sem setor ou quadra no bayface do IBGE 0500-0241P-0-100"
      },
      "geometry": {
         "type": "Point",
         "coordinates": [-38.279071,-9.647163]
      }
    }
  ]
}
