{
  "type": "FeatureCollection",
  "source": "IBGE CNEFE + Faces de Logradouros - 2022",
  "generator": "CSV-CNEFE2GeoJSON.lua 1.5.7 - fidelis.assis@gmail.com",
  "date": "2025-02-02T09:05:28-0300",
  "features": [
    {
      "type": "Feature",
      "properties": { 
      "IBGE:COD_UNICO_ENDERECO": "112585459",
      "addr:housenumber": "5",
      "addr:postcode": "48619-899",
      "addr:suburb": "Pau de Colher",
      "building": "yes",
      "fixme": "Verificar coordenadas",
      "note": "Sem setor ou quadra no bayface do IBGE 0500-0123P-0-79"
      },
      "geometry": {
         "type": "Point",
         "coordinates": [-38.31779,-9.657683]
      }
    },
    {
      "type": "Feature",
      "properties": { 
      "IBGE:COD_UNICO_ENDERECO": "112586085",
      "addr:housenumber": "3",
      "addr:postcode": "48619-899",
      "addr:suburb": "Pau de Colher",
      "building": "yes",
      "fixme": "Verificar coordenadas",
      "note": "Sem setor ou quadra no bayface do IBGE 0500-0123P-0-79"
      },
      "geometry": {
         "type": "Point",
         "coordinates": [-38.318054,-9.657588]
      }
    },
    {
      "type": "Feature",
      "properties": { 
      "IBGE:COD_UNICO_ENDERECO": "27414967",
      "addr:housenumber": "2",
      "addr:postcode": "48619-899",
      "addr:street": "Povoado Pau de Colher",
      "addr:suburb": "Pau de Colher",
      "building": "yes",
      "fixme": "Verificar coordenadas",
      "note": "Sem setor ou quadra no bayface do IBGE 0500-0123P-0-78"
      },
      "geometry": {
         "type": "Point",
         "coordinates": [-38.318084,-9.657626]
      }
    }
  ]
}
